eit_sms/__init__.py
eit_sms/config/__init__.py
eit_sms/config/asgi.py
eit_sms/config/settings.py
eit_sms/config/urls.py
eit_sms/config/wsgi.py
eit_sms/sms/__init__.py
eit_sms/sms/filters.py
eit_sms/sms/models.py
eit_sms/sms/serializers.py
eit_sms/sms/tasks.py
eit_sms/sms/urls.py
eit_sms/sms/views.py
eit_sms/sms/migrations/__init__.py
eit_sms-0.2.dist-info/LICENSE
eit_sms-0.2.dist-info/METADATA
eit_sms-0.2.dist-info/WHEEL
eit_sms-0.2.dist-info/top_level.txt
eit_sms-0.2.dist-info/RECORD
