Metadata-Version: 2.1
Name: eit-sms
Version: 0.2
Summary: A Django app to scaffold SMS functions.
Author-email: Kalume Kitsao <kalumewakitsao@gmail.com>
Project-URL: Homepage, https://github.com/kalumewakitsao/eit-sms
Classifier: Environment :: Web Environment
Classifier: Framework :: Django
Classifier: Framework :: Django :: 4.2
Classifier: Intended Audience :: Developers
Classifier: License :: OSI Approved :: BSD License
Classifier: Operating System :: OS Independent
Classifier: Programming Language :: Python
Classifier: Programming Language :: Python :: 3
Classifier: Programming Language :: Python :: 3 :: Only
Classifier: Programming Language :: Python :: 3.9
Classifier: Programming Language :: Python :: 3.10
Classifier: Programming Language :: Python :: 3.11
Classifier: Programming Language :: Python :: 3.12
Classifier: Programming Language :: Python :: 3.13
Classifier: Topic :: Internet :: WWW/HTTP
Classifier: Topic :: Internet :: WWW/HTTP :: Dynamic Content
Requires-Python: >=3.9
License-File: LICENSE
Requires-Dist: dj-database-url
Requires-Dist: Django>=3.2.4
Requires-Dist: ipython
Requires-Dist: djangorestframework
Requires-Dist: django-extensions
Requires-Dist: django-filter
Requires-Dist: psycopg2-binary
